Metadata-Version: 2.1
Name: pyPatchouli
Version: 0.1.1
Summary: Patchouli is LINE app's history text parser.
Home-page: https://github.com/nakasyou/Patchouli
Author: nakasyou
License: MIT
Keywords: line patchouliv history parser
License-File: LICENSE
